LICENSE
MANIFEST.in
README.md
setup.py
analytics_client/__init__.py
analytics_client/client.py
analytics_client/middleware.py
analytics_client/models.py
analytics_client/sample.py
analytics_client/settings.py
analytics_client/tasks.py
django_analytics_client.egg-info/PKG-INFO
django_analytics_client.egg-info/SOURCES.txt
django_analytics_client.egg-info/dependency_links.txt
django_analytics_client.egg-info/top_level.txt