Metadata-Version: 1.0
Name: django-analytics-client
Version: 0.1.4
Summary: Custom analytics client for Django projects.
Home-page: https://github.com/funkbit/django-analytics-client
Author: Funkbit AS
Author-email: post@funkbit.no
License: BSD
Platform: UNKNOWN
Classifier: Development Status :: 3 - Alpha
Classifier: Framework :: Django
Classifier: Intended Audience :: Developers
Classifier: License :: OSI Approved :: BSD License
Classifier: Programming Language :: Python
Classifier: Programming Language :: Python :: 2.6
Classifier: Programming Language :: Python :: 2.7
